<hazardsData><numHazardLevels>2</numHazardLevels><scenarios><scenario id="0"><prob>1.0</prob><hazardLevelAtFacility facName="0">1</hazardLevelAtFacility><hazardLevelAtFacility facName="1">1</hazardLevelAtFacility><hazardLevelAtFacility facName="2">1</hazardLevelAtFacility><hazardLevelAtFacility facName="3">1</hazardLevelAtFacility><hazardLevelAtFacility facName="4">1</hazardLevelAtFacility><hazardLevelAtFacility facName="5">1</hazardLevelAtFacility><hazardLevelAtFacility facName="6">1</hazardLevelAtFacility><hazardLevelAtFacility facName="7">1</hazardLevelAtFacility><hazardLevelAtFacility facName="8">1</hazardLevelAtFacility><hazardLevelAtFacility facName="9">1</hazardLevelAtFacility><hazardLevelAtFacility facName="10">1</hazardLevelAtFacility><hazardLevelAtFacility facName="11">1</hazardLevelAtFacility><hazardLevelAtFacility facName="12">1</hazardLevelAtFacility><hazardLevelAtFacility facName="13">1</hazardLevelAtFacility><hazardLevelAtFacility facName="14">1</hazardLevelAtFacility><hazardLevelAtFacility facName="15">1</hazardLevelAtFacility><hazardLevelAtFacility facName="16">1</hazardLevelAtFacility><hazardLevelAtFacility facName="17">1</hazardLevelAtFacility><hazardLevelAtFacility facName="18">1</hazardLevelAtFacility><hazardLevelAtFacility facName="19">1</hazardLevelAtFacility><hazardLevelAtFacility facName="20">1</hazardLevelAtFacility><hazardLevelAtFacility facName="21">1</hazardLevelAtFacility><hazardLevelAtFacility facName="22">1</hazardLevelAtFacility><hazardLevelAtFacility facName="23">1</hazardLevelAtFacility><hazardLevelAtFacility facName="24">1</hazardLevelAtFacility><hazardLevelAtFacility facName="25">1</hazardLevelAtFacility><hazardLevelAtFacility facName="26">1</hazardLevelAtFacility><hazardLevelAtFacility facName="27">1</hazardLevelAtFacility><hazardLevelAtFacility facName="28">1</hazardLevelAtFacility><hazardLevelAtFacility facName="29">1</hazardLevelAtFacility><hazardLevelAtFacility facName="30">1</hazardLevelAtFacility><hazardLevelAtFacility facName="31">1</hazardLevelAtFacility><hazardLevelAtFacility facName="32">1</hazardLevelAtFacility><hazardLevelAtFacility facName="33">1</hazardLevelAtFacility><hazardLevelAtFacility facName="34">1</hazardLevelAtFacility><hazardLevelAtFacility facName="35">1</hazardLevelAtFacility><hazardLevelAtFacility facName="36">1</hazardLevelAtFacility><hazardLevelAtFacility facName="37">1</hazardLevelAtFacility><hazardLevelAtFacility facName="38">1</hazardLevelAtFacility><hazardLevelAtFacility facName="39">1</hazardLevelAtFacility><hazardLevelAtFacility facName="40">1</hazardLevelAtFacility><hazardLevelAtFacility facName="41">1</hazardLevelAtFacility><hazardLevelAtFacility facName="42">1</hazardLevelAtFacility><hazardLevelAtFacility facName="43">1</hazardLevelAtFacility><hazardLevelAtFacility facName="44">1</hazardLevelAtFacility><hazardLevelAtFacility facName="45">1</hazardLevelAtFacility><hazardLevelAtFacility facName="46">1</hazardLevelAtFacility><hazardLevelAtFacility facName="47">1</hazardLevelAtFacility><hazardLevelAtFacility facName="48">1</hazardLevelAtFacility></scenario></scenarios></hazardsData>